aqara_python_sdk-0.0.3.2.dist-info/METADATA
aqara_python_sdk-0.0.3.2.dist-info/WHEEL
aqara_python_sdk-0.0.3.2.dist-info/entry_points.txt
aqara_python_sdk-0.0.3.2.dist-info/licenses/LICENSE
aqara_python_sdk/__init__.py
aqara_python_sdk/client.py
aqara_python_sdk/consts.py
aqara_python_sdk/control.py
aqara_python_sdk/enums/__init__.py
aqara_python_sdk/enums/device_type.py
aqara_python_sdk/enums/query.py
aqara_python_sdk/manager/__init__.py
aqara_python_sdk/manager/device.py
aqara_python_sdk/manager/position.py
aqara_python_sdk/manager/scene.py
aqara_python_sdk/models/__init__.py
aqara_python_sdk/models/base.py
aqara_python_sdk/models/client.py
aqara_python_sdk/models/contract.py
aqara_python_sdk/query/__init__.py
aqara_python_sdk/query/control.py
aqara_python_sdk/sub_control/__init__.py
aqara_python_sdk/sub_control/base.py
aqara_python_sdk/sub_control/light.py
aqara_python_sdk/sub_control/switch.py
aqara_python_sdk/utils/__init__.py
aqara_python_sdk/utils/json_encoder.py
aqara_python_sdk/utils/sign.py
aqara_python_sdk-0.0.3.2.dist-info/RECORD
