Metadata-Version: 2.1
Name: aqara_python_sdk
Version: 0.0.3.2
Summary: Awesome python sdk for Aqara development
Author-Email: Daniel Cao <448219947@qq.com>
License: MIT
Requires-Python: >=3.11
Requires-Dist: requests>=2.32.3
